clust/__init__.py
clust/__main__.py
clust/clustpipeline.py
clust/scripts/__init__.py
clust/scripts/clustering.py
clust/scripts/datastructures.py
clust/scripts/eigengene.py
clust/scripts/glob.py
clust/scripts/graphics.py
clust/scripts/io.py
clust/scripts/mnplots.py
clust/scripts/numeric.py
clust/scripts/output.py
clust/scripts/postprocess_results.py
clust/scripts/preprocess_data.py
clust/scripts/statistical.py
clust/scripts/uncles.py
clust/scripts/validation.py
clust-1.18.0.dist-info/LICENSE
clust-1.18.0.dist-info/METADATA
clust-1.18.0.dist-info/WHEEL
clust-1.18.0.dist-info/entry_points.txt
clust-1.18.0.dist-info/top_level.txt
clust-1.18.0.dist-info/RECORD
