Metadata-Version: 2.1
Name: clust
Version: 1.18.0
Summary: Optimised consensus clustering of multiple heterogeneous datasets
Home-page: https://github.com/baselabujamous/clust
Author: Basel Abu-Jamous
Author-email: baselabujamous@gmail.com
License: OSI Approved :: GNU Lesser General Public License v3 (LGPLv3)
Classifier: Development Status :: 3 - Alpha
Classifier: Intended Audience :: Science/Research
Classifier: Topic :: Software Development :: Build Tools
Classifier: License :: OSI Approved :: GNU Lesser General Public License v3 (LGPLv3)
Classifier: Programming Language :: Python :: 3
License-File: LICENSE
Requires-Dist: joblib (>=1.2.0)
Requires-Dist: portalocker (>=2.6.0)
Requires-Dist: numpy (>=1.23.4)
Requires-Dist: scipy (>=1.9.3)
Requires-Dist: pandas (>=1.5.0)
Requires-Dist: matplotlib (>=3.6.1)
Requires-Dist: scikit-learn (>=1.1.3)
